svbridge.py
simple_vertex_bridge-0.3.1.dist-info/licenses/LICENSE
simple_vertex_bridge-0.3.1.dist-info/METADATA
simple_vertex_bridge-0.3.1.dist-info/WHEEL
simple_vertex_bridge-0.3.1.dist-info/entry_points.txt
simple_vertex_bridge-0.3.1.dist-info/top_level.txt
simple_vertex_bridge-0.3.1.dist-info/RECORD
