Metadata-Version: 2.4
Name: simple-vertex-bridge
Version: 0.3.1
Summary: A simple Vertex AI proxy that automatically refresh tokens for you.
Author-email: zetaloop <zetaloop@outlook.com>
License-Expression: Unlicense
Project-URL: repository, https://github.com/zetaloop/simple-vertex-bridge
Classifier: Development Status :: 4 - Beta
Classifier: Programming Language :: Python :: 3
Classifier: Programming Language :: Python :: 3.13
Classifier: Operating System :: OS Independent
Classifier: Topic :: Internet :: Proxy Servers
Requires-Python: >=3.13
License-File: LICENSE
Requires-Dist: google-auth
Requires-Dist: fastapi
Requires-Dist: uvicorn
Requires-Dist: requests
Requires-Dist: httpx
Requires-Dist: h2
Requires-Dist: apscheduler
Dynamic: license-file
